dbtenv_dbt_alias/__init__.py
dbtenv_dbt_alias-2.2.2.dist-info/entry_points.txt
dbtenv_dbt_alias-2.2.2.dist-info/WHEEL
dbtenv_dbt_alias-2.2.2.dist-info/METADATA
dbtenv_dbt_alias-2.2.2.dist-info/RECORD
